{
  "lastUpdated": "2026-05-08T05:11:10.756Z",
  "totalSites": 31,
  "sitesWithBanners": 30,
  "totalBanners": 117,
  "sites": [
    {
      "siteName": "Polo Digital 10",
      "siteUrl": "https://www.polodigital10.com",
      "status": "found",
      "bannersFound": 6,
      "screenshots": [
        {
          "url": "https://www.polodigital10.com",
          "image": "page_1_section_1_1778216198024.png",
          "matches": [
            {
              "referenceImage": "metro-campaign.png",
              "confidence": 0.719161331653595,
              "method": "multiscale"
            },
            {
              "referenceImage": "obras-campaign.png",
              "confidence": 0.643494188785553,
              "method": "multiscale"
            },
            {
              "referenceImage": "policia-campaign.png",
              "confidence": 0.45837610960006714,
              "method": "multiscale"
            }
          ]
        },
        {
          "url": "https://www.polodigital10.com/",
          "image": "page_2_section_1_1778216212912.png",
          "matches": [
            {
              "referenceImage": "metro-campaign.png",
              "confidence": 0.719160795211792,
              "method": "multiscale"
            },
            {
              "referenceImage": "obras-campaign.png",
              "confidence": 0.62416011095047,
              "method": "multiscale"
            },
            {
              "referenceImage": "policia-campaign.png",
              "confidence": 0.45837610960006714,
              "method": "multiscale"
            }
          ]
        }
      ]
    },
    {
      "siteName": "Neyba Informativo",
      "siteUrl": "https://www.neybainformativo.net",
      "status": "found",
      "bannersFound": 6,
      "screenshots": [
        {
          "url": "https://www.neybainformativo.net",
          "image": "page_1_section_1_1778216228196.png",
          "matches": [
            {
              "referenceImage": "metro-campaign.png",
              "confidence": 0.5341609120368958,
              "method": "multiscale"
            },
            {
              "referenceImage": "obras-campaign.png",
              "confidence": 0.5852505564689636,
              "method": "multiscale"
            },
            {
              "referenceImage": "policia-campaign.png",
              "confidence": 0.9974586367607117,
              "method": "multiscale"
            }
          ]
        },
        {
          "url": "https://www.neybainformativo.net/",
          "image": "page_2_section_1_1778216245073.png",
          "matches": [
            {
              "referenceImage": "metro-campaign.png",
              "confidence": 0.5341609120368958,
              "method": "multiscale"
            },
            {
              "referenceImage": "obras-campaign.png",
              "confidence": 0.5852505564689636,
              "method": "multiscale"
            },
            {
              "referenceImage": "policia-campaign.png",
              "confidence": 0.9974586367607117,
              "method": "multiscale"
            }
          ]
        }
      ]
    },
    {
      "siteName": "Diario Altagraciano",
      "siteUrl": "https://www.altagraciano.com",
      "status": "not_found",
      "bannersFound": 0,
      "screenshots": []
    },
    {
      "siteName": "Noti Digital RD",
      "siteUrl": "https://www.notidigitalrd.com.do",
      "status": "found",
      "bannersFound": 3,
      "screenshots": [
        {
          "url": "https://www.notidigitalrd.com.do",
          "image": "page_1_section_1_1778216264754.png",
          "matches": [
            {
              "referenceImage": "metro-campaign.png",
              "confidence": 0.5499857664108276,
              "method": "multiscale"
            },
            {
              "referenceImage": "obras-campaign.png",
              "confidence": 0.5673733949661255,
              "method": "multiscale"
            },
            {
              "referenceImage": "policia-campaign.png",
              "confidence": 0.47406065464019775,
              "method": "multiscale"
            }
          ]
        }
      ]
    },
    {
      "siteName": "La Voz de San Juan",
      "siteUrl": "https://www.lavozdesanjuan.net",
      "status": "found",
      "bannersFound": 5,
      "screenshots": [
        {
          "url": "https://www.lavozdesanjuan.net",
          "image": "page_1_section_1_1778216284702.png",
          "matches": [
            {
              "referenceImage": "metro-campaign.png",
              "confidence": 0.541321873664856,
              "method": "multiscale"
            },
            {
              "referenceImage": "obras-campaign.png",
              "confidence": 0.5893205404281616,
              "method": "multiscale"
            },
            {
              "referenceImage": "policia-campaign.png",
              "confidence": 0.45961326360702515,
              "method": "multiscale"
            }
          ]
        },
        {
          "url": "https://www.lavozdesanjuan.net/",
          "image": "page_2_section_1_1778216303226.png",
          "matches": [
            {
              "referenceImage": "metro-campaign.png",
              "confidence": 0.5413212776184082,
              "method": "multiscale"
            },
            {
              "referenceImage": "obras-campaign.png",
              "confidence": 0.5717770457267761,
              "method": "multiscale"
            }
          ]
        }
      ]
    },
    {
      "siteName": "Despierta El Sur",
      "siteUrl": "https://www.despiertaelsur.com",
      "status": "found",
      "bannersFound": 2,
      "screenshots": [
        {
          "url": "https://www.despiertaelsur.com",
          "image": "page_1_section_1_1778216324017.png",
          "matches": [
            {
              "referenceImage": "metro-campaign.png",
              "confidence": 0.5261972546577454,
              "method": "multiscale"
            },
            {
              "referenceImage": "obras-campaign.png",
              "confidence": 0.5965622067451477,
              "method": "multiscale"
            }
          ]
        }
      ]
    },
    {
      "siteName": "El Jacaguero",
      "siteUrl": "https://www.eljacaguero.com.do",
      "status": "found",
      "bannersFound": 2,
      "screenshots": [
        {
          "url": "https://www.eljacaguero.com.do",
          "image": "page_1_section_1_1778216341800.png",
          "matches": [
            {
              "referenceImage": "metro-campaign.png",
              "confidence": 0.5108097195625305,
              "method": "multiscale"
            },
            {
              "referenceImage": "obras-campaign.png",
              "confidence": 0.5550418496131897,
              "method": "multiscale"
            }
          ]
        }
      ]
    },
    {
      "siteName": "Caribbean Digital",
      "siteUrl": "https://www.caribbeandigital.net",
      "status": "found",
      "bannersFound": 2,
      "screenshots": [
        {
          "url": "https://www.caribbeandigital.net",
          "image": "page_1_section_1_1778216357104.png",
          "matches": [
            {
              "referenceImage": "metro-campaign.png",
              "confidence": 0.5492603778839111,
              "method": "multiscale"
            },
            {
              "referenceImage": "obras-campaign.png",
              "confidence": 0.6172916889190674,
              "method": "multiscale"
            }
          ]
        }
      ]
    },
    {
      "siteName": "Noticias Breves JAZB",
      "siteUrl": "https://noticiasbrevesjazb.com",
      "status": "found",
      "bannersFound": 4,
      "screenshots": [
        {
          "url": "https://noticiasbrevesjazb.com",
          "image": "page_1_section_1_1778216376056.png",
          "matches": [
            {
              "referenceImage": "metro-campaign.png",
              "confidence": 0.5515058040618896,
              "method": "multiscale"
            },
            {
              "referenceImage": "obras-campaign.png",
              "confidence": 0.5683929324150085,
              "method": "multiscale"
            }
          ]
        },
        {
          "url": "https://noticiasbrevesjazb.com/feminicidio-en-el-seibo-hombre-quema-a-su-pareja/",
          "image": "page_2_section_1_1778216394625.png",
          "matches": [
            {
              "referenceImage": "metro-campaign.png",
              "confidence": 0.5120423436164856,
              "method": "multiscale"
            },
            {
              "referenceImage": "obras-campaign.png",
              "confidence": 0.5456679463386536,
              "method": "multiscale"
            }
          ]
        }
      ]
    },
    {
      "siteName": "10 Noticias",
      "siteUrl": "https://www.10noticias.com.do",
      "status": "found",
      "bannersFound": 5,
      "screenshots": [
        {
          "url": "https://www.10noticias.com.do",
          "image": "page_1_section_1_1778216422154.png",
          "matches": [
            {
              "referenceImage": "metro-campaign.png",
              "confidence": 0.5719038248062134,
              "method": "multiscale"
            },
            {
              "referenceImage": "obras-campaign.png",
              "confidence": 0.6141577363014221,
              "method": "multiscale"
            },
            {
              "referenceImage": "policia-campaign.png",
              "confidence": 0.47138711810112,
              "method": "multiscale"
            }
          ]
        },
        {
          "url": "https://www.10noticias.com.do/?publicidad_click=69073",
          "image": "page_2_section_1_1778216440944.png",
          "matches": [
            {
              "referenceImage": "metro-campaign.png",
              "confidence": 0.5283833742141724,
              "method": "multiscale"
            },
            {
              "referenceImage": "obras-campaign.png",
              "confidence": 0.5856738090515137,
              "method": "multiscale"
            }
          ]
        }
      ]
    },
    {
      "siteName": "Gobernanzas Digital",
      "siteUrl": "https://gobernanzasdigital.com",
      "status": "found",
      "bannersFound": 4,
      "screenshots": [
        {
          "url": "https://gobernanzasdigital.com",
          "image": "page_1_section_1_1778216450113.png",
          "matches": [
            {
              "referenceImage": "metro-campaign.png",
              "confidence": 0.5319651365280151,
              "method": "multiscale"
            },
            {
              "referenceImage": "obras-campaign.png",
              "confidence": 0.5673564076423645,
              "method": "multiscale"
            }
          ]
        },
        {
          "url": "https://gobernanzasdigital.com/",
          "image": "page_2_section_1_1778216465395.png",
          "matches": [
            {
              "referenceImage": "metro-campaign.png",
              "confidence": 0.5319651365280151,
              "method": "multiscale"
            },
            {
              "referenceImage": "obras-campaign.png",
              "confidence": 0.5673564076423645,
              "method": "multiscale"
            }
          ]
        }
      ]
    },
    {
      "siteName": "M2 Noticias",
      "siteUrl": "https://m2noticias.com",
      "status": "found",
      "bannersFound": 4,
      "screenshots": [
        {
          "url": "https://m2noticias.com",
          "image": "page_1_section_1_1778216481077.png",
          "matches": [
            {
              "referenceImage": "metro-campaign.png",
              "confidence": 0.5438929796218872,
              "method": "multiscale"
            },
            {
              "referenceImage": "obras-campaign.png",
              "confidence": 0.5622802376747131,
              "method": "multiscale"
            }
          ]
        },
        {
          "url": "https://m2noticias.com/",
          "image": "page_2_section_1_1778216498205.png",
          "matches": [
            {
              "referenceImage": "metro-campaign.png",
              "confidence": 0.5438929796218872,
              "method": "multiscale"
            },
            {
              "referenceImage": "obras-campaign.png",
              "confidence": 0.5622802376747131,
              "method": "multiscale"
            }
          ]
        }
      ]
    },
    {
      "siteName": "Factor Mundo",
      "siteUrl": "https://factormundo.com",
      "status": "found",
      "bannersFound": 4,
      "screenshots": [
        {
          "url": "https://factormundo.com",
          "image": "page_1_section_1_1778216516729.png",
          "matches": [
            {
              "referenceImage": "metro-campaign.png",
              "confidence": 0.57216876745224,
              "method": "multiscale"
            },
            {
              "referenceImage": "obras-campaign.png",
              "confidence": 0.5917581915855408,
              "method": "multiscale"
            }
          ]
        },
        {
          "url": "https://factormundo.com/iran-acusa-a-ee-uu-de-violar-el-alto-el-fuego-tras-ataques-en-ormuz/",
          "image": "page_2_section_1_1778216534490.png",
          "matches": [
            {
              "referenceImage": "metro-campaign.png",
              "confidence": 0.5233899354934692,
              "method": "multiscale"
            },
            {
              "referenceImage": "obras-campaign.png",
              "confidence": 0.5525611042976379,
              "method": "multiscale"
            }
          ]
        }
      ]
    },
    {
      "siteName": "Conocer al Autor",
      "siteUrl": "https://conoceralautor.do",
      "status": "found",
      "bannersFound": 6,
      "screenshots": [
        {
          "url": "https://conoceralautor.do",
          "image": "page_1_section_1_1778216546814.png",
          "matches": [
            {
              "referenceImage": "metro-campaign.png",
              "confidence": 0.5745367407798767,
              "method": "multiscale"
            },
            {
              "referenceImage": "obras-campaign.png",
              "confidence": 0.6151281595230103,
              "method": "multiscale"
            },
            {
              "referenceImage": "policia-campaign.png",
              "confidence": 0.45826512575149536,
              "method": "multiscale"
            }
          ]
        },
        {
          "url": "https://conoceralautor.do/",
          "image": "page_2_section_1_1778216564178.png",
          "matches": [
            {
              "referenceImage": "metro-campaign.png",
              "confidence": 0.5757918953895569,
              "method": "multiscale"
            },
            {
              "referenceImage": "obras-campaign.png",
              "confidence": 0.6199874877929688,
              "method": "multiscale"
            },
            {
              "referenceImage": "policia-campaign.png",
              "confidence": 0.45826512575149536,
              "method": "multiscale"
            }
          ]
        }
      ]
    },
    {
      "siteName": "El Vespertino",
      "siteUrl": "https://www.elvespertino.com",
      "status": "found",
      "bannersFound": 2,
      "screenshots": [
        {
          "url": "https://www.elvespertino.com",
          "image": "page_1_section_1_1778216587503.png",
          "matches": [
            {
              "referenceImage": "metro-campaign.png",
              "confidence": 0.5403817892074585,
              "method": "multiscale"
            },
            {
              "referenceImage": "obras-campaign.png",
              "confidence": 0.6047523617744446,
              "method": "multiscale"
            }
          ]
        }
      ]
    },
    {
      "siteName": "Entre Notas",
      "siteUrl": "https://www.entrenotas.com.do",
      "status": "found",
      "bannersFound": 4,
      "screenshots": [
        {
          "url": "https://www.entrenotas.com.do",
          "image": "page_1_section_1_1778216608580.png",
          "matches": [
            {
              "referenceImage": "metro-campaign.png",
              "confidence": 0.543238639831543,
              "method": "multiscale"
            },
            {
              "referenceImage": "obras-campaign.png",
              "confidence": 0.6004278659820557,
              "method": "multiscale"
            }
          ]
        },
        {
          "url": "https://www.entrenotas.com.do/",
          "image": "page_2_section_1_1778216624177.png",
          "matches": [
            {
              "referenceImage": "metro-campaign.png",
              "confidence": 0.543238639831543,
              "method": "multiscale"
            },
            {
              "referenceImage": "obras-campaign.png",
              "confidence": 0.6004278659820557,
              "method": "multiscale"
            }
          ]
        }
      ]
    },
    {
      "siteName": "Expreso Digital",
      "siteUrl": "https://expresodigital.com.do",
      "status": "found",
      "bannersFound": 4,
      "screenshots": [
        {
          "url": "https://expresodigital.com.do",
          "image": "page_1_section_1_1778216645532.png",
          "matches": [
            {
              "referenceImage": "metro-campaign.png",
              "confidence": 0.5656754374504089,
              "method": "multiscale"
            },
            {
              "referenceImage": "obras-campaign.png",
              "confidence": 0.5629916787147522,
              "method": "multiscale"
            }
          ]
        },
        {
          "url": "https://expresodigital.com.do/trump-y-lula-rebajan-tensiones-con-una-reunion-en-la-casa-blanca-mas-larga-de-lo-esperado/",
          "image": "page_2_section_1_1778216665621.png",
          "matches": [
            {
              "referenceImage": "metro-campaign.png",
              "confidence": 0.5530027151107788,
              "method": "multiscale"
            },
            {
              "referenceImage": "obras-campaign.png",
              "confidence": 0.5743538737297058,
              "method": "multiscale"
            }
          ]
        }
      ]
    },
    {
      "siteName": "Valor Noticioso",
      "siteUrl": "https://www.valornoticioso.com",
      "status": "found",
      "bannersFound": 2,
      "screenshots": [
        {
          "url": "https://www.valornoticioso.com",
          "image": "page_1_section_1_1778216692795.png",
          "matches": [
            {
              "referenceImage": "metro-campaign.png",
              "confidence": 0.5455636382102966,
              "method": "multiscale"
            },
            {
              "referenceImage": "obras-campaign.png",
              "confidence": 0.5762476921081543,
              "method": "multiscale"
            }
          ]
        }
      ]
    },
    {
      "siteName": "Revista Business",
      "siteUrl": "https://revistabusiness.com.do",
      "status": "found",
      "bannersFound": 6,
      "screenshots": [
        {
          "url": "https://revistabusiness.com.do",
          "image": "page_1_section_1_1778216711399.png",
          "matches": [
            {
              "referenceImage": "metro-campaign.png",
              "confidence": 0.555217444896698,
              "method": "multiscale"
            },
            {
              "referenceImage": "obras-campaign.png",
              "confidence": 0.6220283508300781,
              "method": "multiscale"
            },
            {
              "referenceImage": "policia-campaign.png",
              "confidence": 0.45139896869659424,
              "method": "multiscale"
            }
          ]
        },
        {
          "url": "https://revistabusiness.com.do/",
          "image": "page_2_section_1_1778216726311.png",
          "matches": [
            {
              "referenceImage": "metro-campaign.png",
              "confidence": 0.555217444896698,
              "method": "multiscale"
            },
            {
              "referenceImage": "obras-campaign.png",
              "confidence": 0.6220283508300781,
              "method": "multiscale"
            },
            {
              "referenceImage": "policia-campaign.png",
              "confidence": 0.45139896869659424,
              "method": "multiscale"
            }
          ]
        }
      ]
    },
    {
      "siteName": "Armario Libre",
      "siteUrl": "https://armariolibre.com.do",
      "status": "found",
      "bannersFound": 4,
      "screenshots": [
        {
          "url": "https://armariolibre.com.do",
          "image": "page_1_section_1_1778216743286.png",
          "matches": [
            {
              "referenceImage": "metro-campaign.png",
              "confidence": 0.5378941893577576,
              "method": "multiscale"
            },
            {
              "referenceImage": "obras-campaign.png",
              "confidence": 0.5672887563705444,
              "method": "multiscale"
            }
          ]
        },
        {
          "url": "https://www.armariolibre.com.do/wp-login.php?action=lostpassword&redirect_to=https%3A%2F%2Fwww.armariolibre.com.do%2F",
          "image": "page_2_section_1_1778216758730.png",
          "matches": [
            {
              "referenceImage": "metro-campaign.png",
              "confidence": 0.457944393157959,
              "method": "multiscale"
            },
            {
              "referenceImage": "obras-campaign.png",
              "confidence": 0.5303679704666138,
              "method": "multiscale"
            }
          ]
        }
      ]
    },
    {
      "siteName": "El Pregonero RD",
      "siteUrl": "https://elpregonerord.com",
      "status": "found",
      "bannersFound": 4,
      "screenshots": [
        {
          "url": "https://elpregonerord.com",
          "image": "page_1_section_1_1778216763645.png",
          "matches": [
            {
              "referenceImage": "metro-campaign.png",
              "confidence": 0.5460711717605591,
              "method": "multiscale"
            },
            {
              "referenceImage": "obras-campaign.png",
              "confidence": 0.5518890619277954,
              "method": "multiscale"
            }
          ]
        },
        {
          "url": "https://elpregonerord.com/",
          "image": "page_2_section_1_1778216780911.png",
          "matches": [
            {
              "referenceImage": "metro-campaign.png",
              "confidence": 0.5460711717605591,
              "method": "multiscale"
            },
            {
              "referenceImage": "obras-campaign.png",
              "confidence": 0.5518890619277954,
              "method": "multiscale"
            }
          ]
        }
      ]
    },
    {
      "siteName": "Diario Noticioso RD",
      "siteUrl": "https://diarionoticiosord.com",
      "status": "found",
      "bannersFound": 4,
      "screenshots": [
        {
          "url": "https://diarionoticiosord.com",
          "image": "page_1_section_1_1778216798887.png",
          "matches": [
            {
              "referenceImage": "metro-campaign.png",
              "confidence": 0.5334998369216919,
              "method": "multiscale"
            },
            {
              "referenceImage": "obras-campaign.png",
              "confidence": 0.5691953897476196,
              "method": "multiscale"
            }
          ]
        },
        {
          "url": "https://www.diarionoticiosord.com/",
          "image": "page_2_section_1_1778216814702.png",
          "matches": [
            {
              "referenceImage": "metro-campaign.png",
              "confidence": 0.5334998369216919,
              "method": "multiscale"
            },
            {
              "referenceImage": "obras-campaign.png",
              "confidence": 0.60869300365448,
              "method": "multiscale"
            }
          ]
        }
      ]
    },
    {
      "siteName": "Nizaero",
      "siteUrl": "https://nizaero.com",
      "status": "found",
      "bannersFound": 4,
      "screenshots": [
        {
          "url": "https://nizaero.com",
          "image": "page_1_section_1_1778216836618.png",
          "matches": [
            {
              "referenceImage": "metro-campaign.png",
              "confidence": 0.5259447693824768,
              "method": "multiscale"
            },
            {
              "referenceImage": "obras-campaign.png",
              "confidence": 0.5801007747650146,
              "method": "multiscale"
            }
          ]
        },
        {
          "url": "https://nizaero.com/category/de-nizao/",
          "image": "page_2_section_1_1778216854505.png",
          "matches": [
            {
              "referenceImage": "metro-campaign.png",
              "confidence": 0.5271891355514526,
              "method": "multiscale"
            },
            {
              "referenceImage": "obras-campaign.png",
              "confidence": 0.5829993486404419,
              "method": "multiscale"
            }
          ]
        }
      ]
    },
    {
      "siteName": "Fuente Noticias",
      "siteUrl": "https://fuentenoticias.com",
      "status": "found",
      "bannersFound": 1,
      "screenshots": [
        {
          "url": "https://fuentenoticias.com",
          "image": "page_1_section_1_1778216868881.png",
          "matches": [
            {
              "referenceImage": "obras-campaign.png",
              "confidence": 0.47683027386665344,
              "method": "multiscale"
            }
          ]
        }
      ]
    },
    {
      "siteName": "Noti Impacto",
      "siteUrl": "https://www.notiimpacto.com.do",
      "status": "found",
      "bannersFound": 4,
      "screenshots": [
        {
          "url": "https://www.notiimpacto.com.do",
          "image": "page_1_section_1_1778216876543.png",
          "matches": [
            {
              "referenceImage": "metro-campaign.png",
              "confidence": 0.5383160710334778,
              "method": "multiscale"
            },
            {
              "referenceImage": "obras-campaign.png",
              "confidence": 0.5691566467285156,
              "method": "multiscale"
            }
          ]
        },
        {
          "url": "https://www.notiimpacto.com.do/",
          "image": "page_2_section_1_1778216891302.png",
          "matches": [
            {
              "referenceImage": "metro-campaign.png",
              "confidence": 0.5383160710334778,
              "method": "multiscale"
            },
            {
              "referenceImage": "obras-campaign.png",
              "confidence": 0.5691566467285156,
              "method": "multiscale"
            }
          ]
        }
      ]
    },
    {
      "siteName": "RD 24 Horas",
      "siteUrl": "https://rd24horas.com",
      "status": "found",
      "bannersFound": 4,
      "screenshots": [
        {
          "url": "https://rd24horas.com",
          "image": "page_1_section_1_1778216908003.png",
          "matches": [
            {
              "referenceImage": "metro-campaign.png",
              "confidence": 0.5389860272407532,
              "method": "multiscale"
            },
            {
              "referenceImage": "obras-campaign.png",
              "confidence": 0.5921679139137268,
              "method": "multiscale"
            }
          ]
        },
        {
          "url": "https://rd24horas.com/category/portada/",
          "image": "page_2_section_1_1778216925436.png",
          "matches": [
            {
              "referenceImage": "metro-campaign.png",
              "confidence": 0.5377551317214966,
              "method": "multiscale"
            },
            {
              "referenceImage": "obras-campaign.png",
              "confidence": 0.612484872341156,
              "method": "multiscale"
            }
          ]
        }
      ]
    },
    {
      "siteName": "Pincel Digital",
      "siteUrl": "https://pinceldigital.do",
      "status": "found",
      "bannersFound": 1,
      "screenshots": [
        {
          "url": "https://pinceldigital.do",
          "image": "page_1_section_1_1778216935556.png",
          "matches": [
            {
              "referenceImage": "obras-campaign.png",
              "confidence": 0.47683149576187134,
              "method": "multiscale"
            }
          ]
        }
      ]
    },
    {
      "siteName": "Imparcial RD",
      "siteUrl": "https://www.imparcialrd.com",
      "status": "found",
      "bannersFound": 6,
      "screenshots": [
        {
          "url": "https://www.imparcialrd.com",
          "image": "page_1_section_1_1778216941144.png",
          "matches": [
            {
              "referenceImage": "metro-campaign.png",
              "confidence": 0.5432154536247253,
              "method": "multiscale"
            },
            {
              "referenceImage": "obras-campaign.png",
              "confidence": 0.6012753248214722,
              "method": "multiscale"
            },
            {
              "referenceImage": "policia-campaign.png",
              "confidence": 0.4514518082141876,
              "method": "multiscale"
            }
          ]
        },
        {
          "url": "https://www.imparcialrd.com/",
          "image": "page_2_section_1_1778216958518.png",
          "matches": [
            {
              "referenceImage": "metro-campaign.png",
              "confidence": 0.550661027431488,
              "method": "multiscale"
            },
            {
              "referenceImage": "obras-campaign.png",
              "confidence": 0.601276695728302,
              "method": "multiscale"
            },
            {
              "referenceImage": "policia-campaign.png",
              "confidence": 0.4514518082141876,
              "method": "multiscale"
            }
          ]
        }
      ]
    },
    {
      "siteName": "Noticias en un Clic",
      "siteUrl": "https://noticiasenunclic.com",
      "status": "found",
      "bannersFound": 4,
      "screenshots": [
        {
          "url": "https://noticiasenunclic.com",
          "image": "page_1_section_1_1778216982163.png",
          "matches": [
            {
              "referenceImage": "metro-campaign.png",
              "confidence": 0.5599541068077087,
              "method": "multiscale"
            },
            {
              "referenceImage": "obras-campaign.png",
              "confidence": 0.5748105645179749,
              "method": "multiscale"
            }
          ]
        },
        {
          "url": "https://noticiasenunclic.com/",
          "image": "page_2_section_1_1778217000846.png",
          "matches": [
            {
              "referenceImage": "metro-campaign.png",
              "confidence": 0.5599541068077087,
              "method": "multiscale"
            },
            {
              "referenceImage": "obras-campaign.png",
              "confidence": 0.5748105645179749,
              "method": "multiscale"
            }
          ]
        }
      ]
    },
    {
      "siteName": "Tu República",
      "siteUrl": "https://turepublica.com",
      "status": "found",
      "bannersFound": 6,
      "screenshots": [
        {
          "url": "https://turepublica.com",
          "image": "page_1_section_1_1778217019162.png",
          "matches": [
            {
              "referenceImage": "metro-campaign.png",
              "confidence": 0.5570839047431946,
              "method": "multiscale"
            },
            {
              "referenceImage": "obras-campaign.png",
              "confidence": 0.5723334550857544,
              "method": "multiscale"
            },
            {
              "referenceImage": "policia-campaign.png",
              "confidence": 0.45635169744491577,
              "method": "multiscale"
            }
          ]
        },
        {
          "url": "https://turepublica.com/contacto/",
          "image": "page_2_section_1_1778217037478.png",
          "matches": [
            {
              "referenceImage": "metro-campaign.png",
              "confidence": 0.4740152955055237,
              "method": "multiscale"
            },
            {
              "referenceImage": "obras-campaign.png",
              "confidence": 0.5420854091644287,
              "method": "multiscale"
            },
            {
              "referenceImage": "policia-campaign.png",
              "confidence": 0.45635169744491577,
              "method": "multiscale"
            }
          ]
        }
      ]
    },
    {
      "siteName": "El Diario",
      "siteUrl": "https://eldiario.do",
      "status": "found",
      "bannersFound": 4,
      "screenshots": [
        {
          "url": "https://eldiario.do",
          "image": "page_1_section_1_1778217045817.png",
          "matches": [
            {
              "referenceImage": "metro-campaign.png",
              "confidence": 0.5458088517189026,
              "method": "multiscale"
            },
            {
              "referenceImage": "obras-campaign.png",
              "confidence": 0.5621312856674194,
              "method": "multiscale"
            }
          ]
        },
        {
          "url": "https://eldiario.do/temas/coronavirus/",
          "image": "page_2_section_1_1778217063495.png",
          "matches": [
            {
              "referenceImage": "metro-campaign.png",
              "confidence": 0.5270400643348694,
              "method": "multiscale"
            },
            {
              "referenceImage": "obras-campaign.png",
              "confidence": 0.5219353437423706,
              "method": "multiscale"
            }
          ]
        }
      ]
    }
  ]
}